botbuilder/integration/aiohttp/__init__.py
botbuilder/integration/aiohttp/about.py
botbuilder/integration/aiohttp/aiohttp_channel_service.py
botbuilder/integration/aiohttp/aiohttp_channel_service_exception_middleware.py
botbuilder/integration/aiohttp/bot_framework_http_adapter.py
botbuilder/integration/aiohttp/bot_framework_http_adapter_integration_base.py
botbuilder/integration/aiohttp/bot_framework_http_client.py
botbuilder/integration/aiohttp/cloud_adapter.py
botbuilder/integration/aiohttp/configuration_bot_framework_authentication.py
botbuilder/integration/aiohttp/configuration_service_client_credential_factory.py
botbuilder/integration/aiohttp/skills/__init__.py
botbuilder/integration/aiohttp/skills/aio_http_client_factory.py
botbuilder/integration/aiohttp/skills/skill_http_client.py
botbuilder/integration/aiohttp/streaming/__init__.py
botbuilder/integration/aiohttp/streaming/aiohttp_web_socket.py
botbuilder_integration_aiohttp-4.16.0.dist-info/METADATA
botbuilder_integration_aiohttp-4.16.0.dist-info/WHEEL
botbuilder_integration_aiohttp-4.16.0.dist-info/top_level.txt
botbuilder_integration_aiohttp-4.16.0.dist-info/RECORD
