Metadata-Version: 2.1
Name: botbuilder-integration-aiohttp
Version: 4.16.0
Summary: Microsoft Bot Framework Bot Builder
Home-page: https://www.github.com/Microsoft/botbuilder-python
Author: Microsoft
License: MIT
Keywords: BotBuilderIntegrationAiohttp,bots,ai,botframework,botbuilder
Platform: UNKNOWN
Classifier: Programming Language :: Python :: 3.7
Classifier: Intended Audience :: Developers
Classifier: License :: OSI Approved :: MIT License
Classifier: Operating System :: OS Independent
Classifier: Development Status :: 5 - Production/Stable
Classifier: Topic :: Scientific/Engineering :: Artificial Intelligence
Requires-Dist: botbuilder-schema ==4.16.0
Requires-Dist: botframework-connector ==4.16.0
Requires-Dist: botbuilder-core ==4.16.0
Requires-Dist: yarl >=1.8.1
Requires-Dist: aiohttp ==3.9.5
